setup.py
CalculadoraTD.egg-info/PKG-INFO
CalculadoraTD.egg-info/SOURCES.txt
CalculadoraTD.egg-info/dependency_links.txt
CalculadoraTD.egg-info/top_level.txt
calculadora/__init__.py
calculadora/calculadora.py