Metadata-Version: 1.0
Name: CalculadoraTD
Version: 0.1
Summary: Calculadora básica
Home-page: https://pypi.python.org/
Author: TransDiv
Author-email: transdiv@gmail.com
License: UNKNOWN
Platform: UNKNOWN
